pywttr_models/__init__.py
pywttr_models/_language.py
pywttr_models/_pydantic.py
pywttr_models/_strenum.py
pywttr_models/af.py
pywttr_models/am.py
pywttr_models/ar.py
pywttr_models/base.py
pywttr_models/be.py
pywttr_models/bn.py
pywttr_models/ca.py
pywttr_models/da.py
pywttr_models/de.py
pywttr_models/el.py
pywttr_models/en.py
pywttr_models/et.py
pywttr_models/fa.py
pywttr_models/fr.py
pywttr_models/gl.py
pywttr_models/hi.py
pywttr_models/hu.py
pywttr_models/ia.py
pywttr_models/id.py
pywttr_models/it.py
pywttr_models/lt.py
pywttr_models/mg.py
pywttr_models/nb.py
pywttr_models/nl.py
pywttr_models/oc.py
pywttr_models/pl.py
pywttr_models/pt_br.py
pywttr_models/py.typed
pywttr_models/ro.py
pywttr_models/ru.py
pywttr_models/ta.py
pywttr_models/th.py
pywttr_models/tr.py
pywttr_models/uk.py
pywttr_models/vi.py
pywttr_models/zh_cn.py
pywttr_models/zh_tw.py
pywttr_models-2.0.2.dist-info/METADATA
pywttr_models-2.0.2.dist-info/WHEEL
pywttr_models-2.0.2.dist-info/licenses/LICENSE
pywttr_models-2.0.2.dist-info/RECORD
