Metadata-Version: 2.4
Name: pywttr-models
Version: 2.0.2
Summary: Internal library for pywttr and aiopywttr
Project-URL: repository, https://github.com/monosans/pywttr-models
Author-email: monosans <hsyqixco@protonmail.com>
License-Expression: MIT
License-File: LICENSE
Keywords: forecast,weather
Classifier: Framework :: Pydantic
Classifier: Framework :: Pydantic :: 2
Classifier: Natural Language :: English
Classifier: Operating System :: OS Independent
Classifier: Programming Language :: Python
Classifier: Programming Language :: Python :: 3 :: Only
Classifier: Programming Language :: Python :: 3.9
Classifier: Programming Language :: Python :: 3.10
Classifier: Programming Language :: Python :: 3.11
Classifier: Programming Language :: Python :: 3.12
Classifier: Programming Language :: Python :: 3.13
Classifier: Programming Language :: Python :: 3.14
Classifier: Programming Language :: Python :: 3.15
Classifier: Typing :: Typed
Requires-Python: >=3.9
Requires-Dist: pydantic>=2
Requires-Dist: typing-extensions>=4.4
